{"pattern":".**a", "dfa":{"graph":{"nodes":{"1":{"pos":"22,44", "height":"0.61", "width":"0.61", "shape":"doublecircle", "y":44.0, "x":22.0}, "0":{"style":"bold", "pos":"120,44", "height":"0.50", "width":"0.50", "shape":"circle", "y":44.0, "x":120.0}}, "edges":[{"endArrow":{"y":58.0, "x":108.0}, "stop":"0", "pos":[{"y":58.0, "x":132.0}, {"y":69.0, "x":136.0}, {"y":80.0, "x":132.0}, {"y":80.0, "x":120.0}, {"y":80.0, "x":112.0}, {"y":75.0, "x":107.0}, {"y":68.0, "x":107.0}], "label":"[^a]", "start":"0", "lp":{"y":88.0, "x":120.0}}, {"endArrow":{"y":36.0, "x":43.0}, "stop":"1", "pos":[{"y":37.0, "x":103.0}, {"y":35.0, "x":97.0}, {"y":33.0, "x":91.0}, {"y":32.0, "x":84.0}, {"y":30.0, "x":75.0}, {"y":30.0, "x":72.0}, {"y":32.0, "x":62.0}, {"y":32.0, "x":59.0}, {"y":33.0, "x":56.0}, {"y":34.0, "x":53.0}], "label":"a", "start":"0", "lp":{"y":40.0, "x":73.0}}, {"endArrow":{"y":49.0, "x":102.0}, "stop":"0", "pos":[{"y":49.0, "x":43.0}, {"y":50.0, "x":49.0}, {"y":51.0, "x":56.0}, {"y":52.0, "x":62.0}, {"y":52.0, "x":72.0}, {"y":53.0, "x":75.0}, {"y":52.0, "x":84.0}, {"y":52.0, "x":87.0}, {"y":51.0, "x":89.0}, {"y":51.0, "x":92.0}], "label":"[^a]", "start":"1", "lp":{"y":60.0, "x":73.0}}, {"endArrow":{"y":61.0, "x":7.0}, "stop":"1", "pos":[{"y":61.0, "x":37.0}, {"y":72.0, "x":41.0}, {"y":84.0, "x":36.0}, {"y":84.0, "x":22.0}, {"y":84.0, "x":12.0}, {"y":78.0, "x":7.0}, {"y":71.0, "x":6.0}], "label":"a", "start":"1", "lp":{"y":92.0, "x":22.0}}]}, "model":{"states":[0, 1], "transitions":[{"start":0, "meta":[0, 3], "edge":"a", "end":1}, {"start":0, "meta":[0], "edge":"\u0000\u0001\u0002\u0003\u0004\u0005\u0006\u0007\b\t\n\u000b\f\r\u000e\u000f\u0010\u0011\u0012\u0013\u0014\u0015\u0016\u0017\u0018\u0019\u001a\u001b\u001c\u001d\u001e\u001f !\"#$%&'()*+,-./0123456789:;<=>?@ABCDEFGHIJKLMNOPQRSTUVWXYZ[\\]^_`bcdefghijklmnopqrstuvwxyz{|}~\u007f\u0080\u0081\u0082\u0083\u0084\u0085\u0086\u0087\u0088\u0089\u008a\u008b\u008c\u008d\u008e\u008f\u0090\u0091\u0092\u0093\u0094\u0095\u0096\u0097\u0098\u0099\u009a\u009b\u009c\u009d\u009e\u009f\u00a0\u00a1\u00a2\u00a3\u00a4\u00a5\u00a6\u00a7\u00a8\u00a9\u00aa\u00ab\u00ac\u00ad\u00ae\u00af\u00b0\u00b1\u00b2\u00b3\u00b4\u00b5\u00b6\u00b7\u00b8\u00b9\u00ba\u00bb\u00bc\u00bd\u00be\u00bf\u00c0\u00c1\u00c2\u00c3\u00c4\u00c5\u00c6\u00c7\u00c8\u00c9\u00ca\u00cb\u00cc\u00cd\u00ce\u00cf\u00d0\u00d1\u00d2\u00d3\u00d4\u00d5\u00d6\u00d7\u00d8\u00d9\u00da\u00db\u00dc\u00dd\u00de\u00df\u00e0\u00e1\u00e2\u00e3\u00e4\u00e5\u00e6\u00e7\u00e8\u00e9\u00ea\u00eb\u00ec\u00ed\u00ee\u00ef\u00f0\u00f1\u00f2\u00f3\u00f4\u00f5\u00f6\u00f7\u00f8\u00f9\u00fa\u00fb\u00fc\u00fd\u00fe\u00ff", "end":0}, {"start":1, "meta":[0, 3], "edge":"a", "end":1}, {"start":1, "meta":[0], "edge":"\u0000\u0001\u0002\u0003\u0004\u0005\u0006\u0007\b\t\n\u000b\f\r\u000e\u000f\u0010\u0011\u0012\u0013\u0014\u0015\u0016\u0017\u0018\u0019\u001a\u001b\u001c\u001d\u001e\u001f !\"#$%&'()*+,-./0123456789:;<=>?@ABCDEFGHIJKLMNOPQRSTUVWXYZ[\\]^_`bcdefghijklmnopqrstuvwxyz{|}~\u007f\u0080\u0081\u0082\u0083\u0084\u0085\u0086\u0087\u0088\u0089\u008a\u008b\u008c\u008d\u008e\u008f\u0090\u0091\u0092\u0093\u0094\u0095\u0096\u0097\u0098\u0099\u009a\u009b\u009c\u009d\u009e\u009f\u00a0\u00a1\u00a2\u00a3\u00a4\u00a5\u00a6\u00a7\u00a8\u00a9\u00aa\u00ab\u00ac\u00ad\u00ae\u00af\u00b0\u00b1\u00b2\u00b3\u00b4\u00b5\u00b6\u00b7\u00b8\u00b9\u00ba\u00bb\u00bc\u00bd\u00be\u00bf\u00c0\u00c1\u00c2\u00c3\u00c4\u00c5\u00c6\u00c7\u00c8\u00c9\u00ca\u00cb\u00cc\u00cd\u00ce\u00cf\u00d0\u00d1\u00d2\u00d3\u00d4\u00d5\u00d6\u00d7\u00d8\u00d9\u00da\u00db\u00dc\u00dd\u00de\u00df\u00e0\u00e1\u00e2\u00e3\u00e4\u00e5\u00e6\u00e7\u00e8\u00e9\u00ea\u00eb\u00ec\u00ed\u00ee\u00ef\u00f0\u00f1\u00f2\u00f3\u00f4\u00f5\u00f6\u00f7\u00f8\u00f9\u00fa\u00fb\u00fc\u00fd\u00fe\u00ff", "end":0}], "finalStates":[1], "initialState":0}}, "nfa":{"graph":{"nodes":{"1":{"pos":"94,18", "height":"0.50", "width":"0.50", "shape":"circle", "y":18.0, "x":94.0}, "0":{"style":"bold", "pos":"18,73", "height":"0.50", "width":"0.50", "shape":"circle", "y":73.0, "x":18.0}, "2":{"pos":"176,73", "height":"0.61", "width":"0.61", "shape":"doublecircle", "y":73.0, "x":176.0}}, "edges":[{"endArrow":{"y":29.0, "x":79.0}, "stop":"1", "pos":[{"y":62.0, "x":33.0}, {"y":54.0, "x":43.0}, {"y":43.0, "x":58.0}, {"y":35.0, "x":71.0}], "label":".", "start":"0", "lp":{"y":55.0, "x":56.0}}, {"endArrow":{"y":75.0, "x":154.0}, "stop":"2", "pos":[{"y":75.0, "x":36.0}, {"y":76.0, "x":48.0}, {"y":78.0, "x":63.0}, {"y":79.0, "x":76.0}, {"y":79.0, "x":92.0}, {"y":79.0, "x":97.0}, {"y":79.0, "x":112.0}, {"y":78.0, "x":122.0}, {"y":78.0, "x":134.0}, {"y":76.0, "x":144.0}], "label":"a", "start":"0", "lp":{"y":87.0, "x":94.0}}, {"endArrow":{"y":32.0, "x":82.0}, "stop":"1", "pos":[{"y":32.0, "x":106.0}, {"y":43.0, "x":110.0}, {"y":54.0, "x":106.0}, {"y":54.0, "x":94.0}, {"y":54.0, "x":86.0}, {"y":49.0, "x":81.0}, {"y":42.0, "x":81.0}], "label":".", "start":"1", "lp":{"y":62.0, "x":94.0}}, {"endArrow":{"y":61.0, "x":158.0}, "stop":"2", "pos":[{"y":28.0, "x":109.0}, {"y":35.0, "x":120.0}, {"y":46.0, "x":136.0}, {"y":55.0, "x":149.0}], "label":"a", "start":"1", "lp":{"y":53.0, "x":133.0}}]}, "model":{"states":[1, 0, 2], "transitions":[{"start":0, "edge":"\u0000\u0001\u0002\u0003\u0004\u0005\u0006\u0007\b\t\n\u000b\f\r\u000e\u000f\u0010\u0011\u0012\u0013\u0014\u0015\u0016\u0017\u0018\u0019\u001a\u001b\u001c\u001d\u001e\u001f !\"#$%&'()*+,-./0123456789:;<=>?@ABCDEFGHIJKLMNOPQRSTUVWXYZ[\\]^_`abcdefghijklmnopqrstuvwxyz{|}~\u007f\u0080\u0081\u0082\u0083\u0084\u0085\u0086\u0087\u0088\u0089\u008a\u008b\u008c\u008d\u008e\u008f\u0090\u0091\u0092\u0093\u0094\u0095\u0096\u0097\u0098\u0099\u009a\u009b\u009c\u009d\u009e\u009f\u00a0\u00a1\u00a2\u00a3\u00a4\u00a5\u00a6\u00a7\u00a8\u00a9\u00aa\u00ab\u00ac\u00ad\u00ae\u00af\u00b0\u00b1\u00b2\u00b3\u00b4\u00b5\u00b6\u00b7\u00b8\u00b9\u00ba\u00bb\u00bc\u00bd\u00be\u00bf\u00c0\u00c1\u00c2\u00c3\u00c4\u00c5\u00c6\u00c7\u00c8\u00c9\u00ca\u00cb\u00cc\u00cd\u00ce\u00cf\u00d0\u00d1\u00d2\u00d3\u00d4\u00d5\u00d6\u00d7\u00d8\u00d9\u00da\u00db\u00dc\u00dd\u00de\u00df\u00e0\u00e1\u00e2\u00e3\u00e4\u00e5\u00e6\u00e7\u00e8\u00e9\u00ea\u00eb\u00ec\u00ed\u00ee\u00ef\u00f0\u00f1\u00f2\u00f3\u00f4\u00f5\u00f6\u00f7\u00f8\u00f9\u00fa\u00fb\u00fc\u00fd\u00fe\u00ff", "end":1}, {"start":0, "edge":"a", "end":2}, {"start":1, "edge":"\u0000\u0001\u0002\u0003\u0004\u0005\u0006\u0007\b\t\n\u000b\f\r\u000e\u000f\u0010\u0011\u0012\u0013\u0014\u0015\u0016\u0017\u0018\u0019\u001a\u001b\u001c\u001d\u001e\u001f !\"#$%&'()*+,-./0123456789:;<=>?@ABCDEFGHIJKLMNOPQRSTUVWXYZ[\\]^_`abcdefghijklmnopqrstuvwxyz{|}~\u007f\u0080\u0081\u0082\u0083\u0084\u0085\u0086\u0087\u0088\u0089\u008a\u008b\u008c\u008d\u008e\u008f\u0090\u0091\u0092\u0093\u0094\u0095\u0096\u0097\u0098\u0099\u009a\u009b\u009c\u009d\u009e\u009f\u00a0\u00a1\u00a2\u00a3\u00a4\u00a5\u00a6\u00a7\u00a8\u00a9\u00aa\u00ab\u00ac\u00ad\u00ae\u00af\u00b0\u00b1\u00b2\u00b3\u00b4\u00b5\u00b6\u00b7\u00b8\u00b9\u00ba\u00bb\u00bc\u00bd\u00be\u00bf\u00c0\u00c1\u00c2\u00c3\u00c4\u00c5\u00c6\u00c7\u00c8\u00c9\u00ca\u00cb\u00cc\u00cd\u00ce\u00cf\u00d0\u00d1\u00d2\u00d3\u00d4\u00d5\u00d6\u00d7\u00d8\u00d9\u00da\u00db\u00dc\u00dd\u00de\u00df\u00e0\u00e1\u00e2\u00e3\u00e4\u00e5\u00e6\u00e7\u00e8\u00e9\u00ea\u00eb\u00ec\u00ed\u00ee\u00ef\u00f0\u00f1\u00f2\u00f3\u00f4\u00f5\u00f6\u00f7\u00f8\u00f9\u00fa\u00fb\u00fc\u00fd\u00fe\u00ff", "end":1}, {"start":1, "edge":"a", "end":2}], "finalStates":[2], "initialState":0}}}